{
    "plantes": [
      {
        "id": 1,
        "nom": "Tomate",
        "image": "https://i.goopics.net/fpgviu.png",
        "description": "Fruit juteux et coloré, très polyvalent en cuisine.",
        "lien_fiche": "fiche-tomate.html",
        "periode_semis": "Février à avril",
        "periode_recolte": "Juillet à septembre",
        "besoin_eau": "Élevé",
        "exposition": "Ensoleillée",
        "distance_plants": 40
      },
      {
        "id": 2,
        "nom": "Pomme de terre",
        "image": "https://i.goopics.net/fpgviu.png",
        "description": "Tubercule polyvalent, largement utilisé en cuisine.",
        "lien_fiche": "fiche-pomme-de-terre.html",
        "periode_semis": "Mars à mai",
        "periode_recolte": "Juin à septembre",
        "besoin_eau": "Moyen",
        "exposition": "Ensoleillée",
        "distance_plants": 30
      },
      {
        "id": 3,
        "nom": "Carotte",
        "image": "https://i.goopics.net/fpgviu.png",
        "description": "Légume racine sucré et croquant, riche en vitamines.",
        "lien_fiche": "fiche-carotte.html",
        "periode_semis": "Mars à juin",
        "periode_recolte": "Juin à octobre",
        "besoin_eau": "Faible à moyen",
        "exposition": "Ensoleillée à mi-ombragée",
        "distance_plants": 5
      },
      {
        "id": 4,
        "nom": "Aubergine",
        "image": "https://i.goopics.net/fpgviu.png",
        "description": "Légume fruit, utilisé dans de nombreuses cuisines du monde.",
        "lien_fiche": "fiche-aubergine.html",
        "periode_semis": "Février à mai",
        "periode_recolte": "Juillet à octobre",
        "besoin_eau": "Élevé",
        "exposition": "Ensoleillée",
        "distance_entre_plants_cm": 60
      },
      {
        "id": 5,
        "nom": "Courgette",
        "image": "https://i.goopics.net/fpgviu.png",
        "description": "Légume tendre et savoureux, parfait pour les plats d'été.",
        "lien_fiche": "fiche-courgette.html",
        "periode_semis": "Avril à juin",
        "periode_recolte": "Juin à octobre",
        "besoin_eau": "Élevé",
        "exposition": "Ensoleillée",
        "distance_entre_plants_cm": 100
      }
    ]
  }
  